wrtty/__init__.py
wrtty/main.py
wrtty-0.6.2.dist-info/LICENSE
wrtty-0.6.2.dist-info/METADATA
wrtty-0.6.2.dist-info/WHEEL
wrtty-0.6.2.dist-info/entry_points.txt
wrtty-0.6.2.dist-info/RECORD
