Metadata-Version: 2.1
Name: wrtty
Version: 0.6.2
Summary: Write Command to Virtual Terminal.
License: MIT
Author: Jeff Moe
Author-email: moe@parrot.codes
Requires-Python: >=3.10,<4.0
Classifier: Development Status :: 4 - Beta
Classifier: Environment :: Console
Classifier: Intended Audience :: Developers
Classifier: Intended Audience :: System Administrators
Classifier: License :: OSI Approved :: MIT License
Classifier: Natural Language :: English
Classifier: Operating System :: POSIX :: Linux
Classifier: Programming Language :: Python :: 3
Classifier: Programming Language :: Python :: 3.10
Classifier: Programming Language :: Python :: 3.11
Classifier: Programming Language :: Python :: 3.12
Classifier: Topic :: System :: Systems Administration
Classifier: Topic :: Utilities
Requires-Dist: setuptools_scm
Project-URL: changelog, https://spacecruft.org/deepcrayon/wrtty/raw/branch/main/CHANGELOG.txt
Project-URL: documentation, https://spacecruft.org/deepcrayon/wrtty
Project-URL: homepage, https://spacecruft.org/deepcrayon/wrtty
Project-URL: issues, https://spacecruft.org/deepcrayon/wrtty/issues
Project-URL: repository, https://spacecruft.org/deepcrayon/wrtty
